Metadata-Version: 2.1
Name: project_test_lib_ciandt
Version: 0.1.0
Summary: Uma biblioteca de exemplo para saudação
Author: Seu Nome
Author-email: seu_email@example.com
Classifier: Programming Language :: Python :: 3
Classifier: License :: OSI Approved :: MIT License
